minicypher/__init__.py
minicypher/clauses.py
minicypher/entities.py
minicypher/functions.py
minicypher/statement.py
minicypher-0.1.3.dist-info/METADATA
minicypher-0.1.3.dist-info/WHEEL
minicypher-0.1.3.dist-info/licenses/LICENSE
minicypher-0.1.3.dist-info/RECORD
