Metadata-Version: 2.4
Name: minicypher
Version: 0.1.3
Summary: Programmatically manipulate Neo4j Cypher language constructs
License-File: LICENSE
Author: Mark A. Jensen
Author-email: mark.jensen@nih.gov
Requires-Python: >=3.10,<4.0
Classifier: Programming Language :: Python :: 3
Classifier: Programming Language :: Python :: 3.10
Classifier: Programming Language :: Python :: 3.11
Classifier: Programming Language :: Python :: 3.12
Classifier: Programming Language :: Python :: 3.13
Classifier: Programming Language :: Python :: 3.14
